Workbook

Sheet Checklist
A1: CHECKLIST DE PREPARATION DU DOSSIER D'AUDIT
A2: Formation en Gestion Financiere d'une ONG Humanitaire · Module 06 · BK-BOOST Ltd.
A4: Categorie | B4: Document requis | C4: Responsable | D4: Statut | E4: Emplacement (dossier partage) | F4: Derniere verification | G4: Commentaire
A5: 1. Comptabilite generale | B5: Grand livre general (periode sous audit) | C5: Finance Officer | D5: Disponible | E5: Drive/Finance/GL | F5: 46239
A6: 1. Comptabilite generale | B6: Journaux de banque et de caisse | C6: Finance Officer | D6: Disponible | E6: Drive/Finance/Journaux | F6: 46239
A7: 1. Comptabilite generale | B7: Rapprochements bancaires mensuels signes | C7: Finance Manager | D7: A rassembler | E7: Drive/Finance/Rapprochements | F7: 46231 | G7: Juillet en attente de signature
A8: 1. Comptabilite generale | B8: Plan comptable et codification par projet/bailleur | C8: Finance Manager | D8: Disponible | E8: Drive/Finance/PlanComptable | F8: 46183
A9: 1. Comptabilite generale | B9: Journal des ecritures de cloture / ajustements | C9: Finance Officer | D9: Disponible | E9: Drive/Finance/Clotures | F9: 46239
A10: 2. Achats et procurement | B10: Dossiers d'achat complets (demande, comparatif, BC, BL, facture) | C10: Logistique | D10: Manquant | E10: Drive/Logistique/Achats | F10: 46235 | G10: BL du dossier ACH-2026-014 introuvable
A11: 2. Achats et procurement | B11: Politique d'achats et seuils de delegation | C11: Finance Manager | D11: Disponible | E11: Drive/Finance/Politiques | F11: 46042
A12: 2. Achats et procurement | B12: Registre des fournisseurs qualifies | C12: Logistique | D12: Disponible | E12: Drive/Logistique/Fournisseurs | F12: 46218
A13: 2. Achats et procurement | B13: Preuves de mise en concurrence au-dessus du seuil bailleur | C13: Logistique | D13: A rassembler | E13: Drive/Logistique/Achats | F13: 46218 | G13: 2 dossiers sur 6 a completer
A14: 2. Achats et procurement | B14: Contrats et accords-cadres fournisseurs | C14: Finance Manager | D14: Disponible | E14: Drive/Finance/Contrats | F14: 46145
A15: 3. Ressources humaines et paie | B15: Contrats de travail du personnel projet | C15: RH | D15: Disponible | E15: Drive/RH/Contrats | F15: 46236
A16: 3. Ressources humaines et paie | B16: Feuilles de temps signees, allocation multi-projets | C16: RH | D16: Disponible | E16: Drive/RH/Timesheets | F16: 46239
A17: 3. Ressources humaines et paie | B17: Registres de paie mensuels | C17: RH | D17: Disponible | E17: Drive/RH/Paie | F17: 46239
A18: 3. Ressources humaines et paie | B18: Preuves de paiement des charges sociales/fiscales | C18: Finance Officer | D18: A rassembler | E18: Drive/Finance/Charges | F18: 46213 | G18: Juin-Juillet a joindre
A19: 3. Ressources humaines et paie | B19: Organigramme et delegations de signature a jour | C19: Finance Manager | D19: Manquant | E19: Drive/Finance/Delegations | F19: 46174 | G19: Delegation Coordinateur Terrain non formalisee
A20: 4. Tresorerie et caisses | B20: Livres de caisse par bureau | C20: Caissiers | D20: Disponible | E20: Drive/Finance/Caisses | F20: 46239
A21: 4. Tresorerie et caisses | B21: Rapprochements de caisse (comptages physiques signes) | C21: Finance Officer | D21: Manquant | E21: Drive/Finance/Caisses | F21: 46218 | G21: Bureau des Cayes : dernier comptage vieux de 3 semaines
A22: 4. Tresorerie et caisses | B22: Fiches d'avances sur justification et leur cloture | C22: Finance Officer | D22: Disponible | E22: Drive/Finance/Avances | F22: 46237
A23: 4. Tresorerie et caisses | B23: Registre des signataires bancaires | C23: Finance Manager | D23: Disponible | E23: Drive/Finance/Banque | F23: 46093
A24: 5. Immobilisations | B24: Registre des immobilisations a jour | C24: Logistique | D24: Disponible | E24: Drive/Logistique/Immobilisations | F24: 46203
A25: 5. Immobilisations | B25: Preuves d'inventaire physique annuel | C25: Logistique | D25: A rassembler | E25: Drive/Logistique/Immobilisations | F25: 46203 | G25: Inventaire du bureau des Cayes a finaliser
A26: 5. Immobilisations | B26: Politique de cession/donation des equipements en fin de projet | C26: Finance Manager | D26: Disponible | E26: Drive/Finance/Politiques | F26: 46042
A27: 6. Accords bailleurs et budgets | B27: Accords de subvention signes et avenants | C27: Finance Manager | D27: Disponible | E27: Drive/Bailleurs/Accords | F27: 46058
A28: 6. Accords bailleurs et budgets | B28: Budgets approuves et versions revisees | C28: Finance Manager | D28: Disponible | E28: Drive/Bailleurs/Budgets | F28: 46130
A29: 6. Accords bailleurs et budgets | B29: Rapports financiers bailleurs soumis (BFU) | C29: Finance Officer | D29: Disponible | E29: Drive/Bailleurs/Rapports | F29: 46235
A30: 6. Accords bailleurs et budgets | B30: Correspondance officielle avec le bailleur | C30: Finance Manager | D30: Disponible | E30: Drive/Bailleurs/Correspondance | F30: 46223
A31: 7. Gouvernance et conformite | B31: Statuts et enregistrement legal a jour | C31: Direction Pays | D31: Disponible | E31: Drive/Direction/Legal | F31: 46032
A32: 7. Gouvernance et conformite | B32: Proces-verbaux du conseil d'administration / comite de pilotage | C32: Direction Pays | D32: A rassembler | E32: Drive/Direction/PV | F32: 46147 | G32: PV du T2 en attente de signature
A33: 7. Gouvernance et conformite | B33: Politique anti-fraude et de lutte contre la corruption | C33: Finance Manager | D33: Disponible | E33: Drive/Finance/Politiques | F33: 46042
A34: 7. Gouvernance et conformite | B34: Registre des conflits d'interets declares | C34: RH | D34: Non applicable | E34: Drive/RH/Conformite | F34: 46042 | G34: Aucun cas declare sur la periode
A35: 8. Suivi des audits precedents | B35: Rapport d'audit et management letter de l'exercice precedent | C35: Finance Manager | D35: Disponible | E35: Drive/Audits/N-1 | F35: 45981
A36: 8. Suivi des audits precedents | B36: Plan d'action correctif precedent et preuves de cloture | C36: Finance Manager | D36: Disponible | E36: Drive/Audits/N-1 | F36: 46111
A37: 8. Suivi des audits precedents | B37: Correspondance avec l'auditeur precedent | C37: Finance Manager | D37: Disponible | E37: Drive/Audits/N-1 | F37: 45996
A39: Cette checklist se met a jour en continu, a chaque cloture mensuelle - pas seulement dans les semaines qui precedent une mission d'audit. Ajoutez des lignes si votre contexte (multi-bureaux, multi-bailleurs) l'exige.

Sheet Tableau de bord
A1: TABLEAU DE BORD - COMPLETUDE DU DOSSIER D'AUDIT
A2: Calcule automatiquement a partir de l'onglet Checklist — ne pas modifier les formules.
A4: Categorie | B4: Documents requis | C4: Documents disponibles | D4: % complet | E4: Documents manquants | F4: Statut global
A5: 1. Comptabilite generale | B5: =COUNTIFS(Checklist!$A$5:$A$37,A5,Checklist!$D$5:$D$37,"<>Non applicable") -> 5 | C5: =COUNTIFS(Checklist!$A$5:$A$37,A5,Checklist!$D$5:$D$37,"Disponible") -> 4 | D5: =IF(B5=0,"",C5/B5) -> 0.8 | E5: =COUNTIFS(Checklist!$A$5:$A$37,A5,Checklist!$D$5:$D$37,"Manquant") -> 0 | F5: =IF(B5=0,"-",IF(D5=1,"Dossier complet",IF(E5>0,"A COMPLETER","En cours"))) -> En cours
A6: 2. Achats et procurement | B6: =COUNTIFS(Checklist!$A$5:$A$37,A6,Checklist!$D$5:$D$37,"<>Non applicable") -> 5 | C6: =COUNTIFS(Checklist!$A$5:$A$37,A6,Checklist!$D$5:$D$37,"Disponible") -> 3 | D6: =IF(B6=0,"",C6/B6) -> 0.6 | E6: =COUNTIFS(Checklist!$A$5:$A$37,A6,Checklist!$D$5:$D$37,"Manquant") -> 1 | F6: =IF(B6=0,"-",IF(D6=1,"Dossier complet",IF(E6>0,"A COMPLETER","En cours"))) -> A COMPLETER
A7: 3. Ressources humaines et paie | B7: =COUNTIFS(Checklist!$A$5:$A$37,A7,Checklist!$D$5:$D$37,"<>Non applicable") -> 5 | C7: =COUNTIFS(Checklist!$A$5:$A$37,A7,Checklist!$D$5:$D$37,"Disponible") -> 3 | D7: =IF(B7=0,"",C7/B7) -> 0.6 | E7: =COUNTIFS(Checklist!$A$5:$A$37,A7,Checklist!$D$5:$D$37,"Manquant") -> 1 | F7: =IF(B7=0,"-",IF(D7=1,"Dossier complet",IF(E7>0,"A COMPLETER","En cours"))) -> A COMPLETER
A8: 4. Tresorerie et caisses | B8: =COUNTIFS(Checklist!$A$5:$A$37,A8,Checklist!$D$5:$D$37,"<>Non applicable") -> 4 | C8: =COUNTIFS(Checklist!$A$5:$A$37,A8,Checklist!$D$5:$D$37,"Disponible") -> 3 | D8: =IF(B8=0,"",C8/B8) -> 0.75 | E8: =COUNTIFS(Checklist!$A$5:$A$37,A8,Checklist!$D$5:$D$37,"Manquant") -> 1 | F8: =IF(B8=0,"-",IF(D8=1,"Dossier complet",IF(E8>0,"A COMPLETER","En cours"))) -> A COMPLETER
A9: 5. Immobilisations | B9: =COUNTIFS(Checklist!$A$5:$A$37,A9,Checklist!$D$5:$D$37,"<>Non applicable") -> 3 | C9: =COUNTIFS(Checklist!$A$5:$A$37,A9,Checklist!$D$5:$D$37,"Disponible") -> 2 | D9: =IF(B9=0,"",C9/B9) -> 0.66666667 | E9: =COUNTIFS(Checklist!$A$5:$A$37,A9,Checklist!$D$5:$D$37,"Manquant") -> 0 | F9: =IF(B9=0,"-",IF(D9=1,"Dossier complet",IF(E9>0,"A COMPLETER","En cours"))) -> En cours
A10: 6. Accords bailleurs et budgets | B10: =COUNTIFS(Checklist!$A$5:$A$37,A10,Checklist!$D$5:$D$37,"<>Non applicable") -> 4 | C10: =COUNTIFS(Checklist!$A$5:$A$37,A10,Checklist!$D$5:$D$37,"Disponible") -> 4 | D10: =IF(B10=0,"",C10/B10) -> 1 | E10: =COUNTIFS(Checklist!$A$5:$A$37,A10,Checklist!$D$5:$D$37,"Manquant") -> 0 | F10: =IF(B10=0,"-",IF(D10=1,"Dossier complet",IF(E10>0,"A COMPLETER","En cours"))) -> Dossier complet
A11: 7. Gouvernance et conformite | B11: =COUNTIFS(Checklist!$A$5:$A$37,A11,Checklist!$D$5:$D$37,"<>Non applicable") -> 3 | C11: =COUNTIFS(Checklist!$A$5:$A$37,A11,Checklist!$D$5:$D$37,"Disponible") -> 2 | D11: =IF(B11=0,"",C11/B11) -> 0.66666667 | E11: =COUNTIFS(Checklist!$A$5:$A$37,A11,Checklist!$D$5:$D$37,"Manquant") -> 0 | F11: =IF(B11=0,"-",IF(D11=1,"Dossier complet",IF(E11>0,"A COMPLETER","En cours"))) -> En cours
A12: 8. Suivi des audits precedents | B12: =COUNTIFS(Checklist!$A$5:$A$37,A12,Checklist!$D$5:$D$37,"<>Non applicable") -> 3 | C12: =COUNTIFS(Checklist!$A$5:$A$37,A12,Checklist!$D$5:$D$37,"Disponible") -> 3 | D12: =IF(B12=0,"",C12/B12) -> 1 | E12: =COUNTIFS(Checklist!$A$5:$A$37,A12,Checklist!$D$5:$D$37,"Manquant") -> 0 | F12: =IF(B12=0,"-",IF(D12=1,"Dossier complet",IF(E12>0,"A COMPLETER","En cours"))) -> Dossier complet
A13: TOTAL GENERAL | B13: =SUM(B5:B12) -> 32 | C13: =SUM(C5:C12) -> 24 | D13: =IF(B13=0,"",C13/B13) -> 0.75 | E13: =SUM(E5:E12) -> 3 | F13: =IF(D13=1,"Dossier complet",IF(E13>0,"A COMPLETER","En cours")) -> A COMPLETER
A15: Une categorie passe automatiquement en "A COMPLETER" des qu'au moins un document y est marque "Manquant" dans l'onglet Checklist.
