Workbook

Sheet Rapport Financier
A1: RAPPORT FINANCIER BAILLEUR — SUIVI PAR RUBRIQUE BUDGÉTAIRE
A2: Module 05 — Rapports Financiers pour Bailleurs · Formation en Gestion Financière d'une ONG Humanitaire · BK-BOOST Ltd.
A4: Organisation : | E4: Période couverte : | G4: Ex. : Trimestre 3 — 01/01/2026 au 31/03/2026
A5: Nom du projet : | E5: Devise de rapportage : | G5: Ex. : EUR / USD
A6: Bailleur : | C6: ECHO / USAID-BHA / Agence onusienne (à préciser) | E6: Taux de change appliqué : | G6: Taux fixe contractuel si ECHO
A7: N° de contrat / award : | E7: Préparé par / date :
A11: N° | B11: Rubrique budgétaire | C11: Budget alloué | D11: Dépenses cumulées à date | E11: Solde disponible | F11: % consommé | G11: Justificatifs (3-way match) statut & référence | H11: Dernière vérification
A12: 1 | B12: A. Ressources humaines | C12: 48000 | D12: 36500 | E12: =C12-D12 -> 11500 | F12: =IF(C12=0,0,D12/C12) -> 0.76041667 | G12: À compléter — statut par pièce (Complet / À confirmer)
A13: 2 | B13: B. Transport & distribution | C13: 62000 | D13: 51200 | E13: =C13-D13 -> 10800 | F13: =IF(C13=0,0,D13/C13) -> 0.82580645 | G13: À compléter — statut par pièce (Complet / À confirmer)
A14: 3 | B14: C. Équipement & fournitures NFI | C14: 95000 | D14: 88400 | E14: =C14-D14 -> 6600 | F14: =IF(C14=0,0,D14/C14) -> 0.93052632 | G14: À compléter — statut par pièce (Complet / À confirmer)
A15: 4 | B15: D. Fonctionnement bureau/base | C15: 18000 | D15: 12100 | E15: =C15-D15 -> 5900 | F15: =IF(C15=0,0,D15/C15) -> 0.67222222 | G15: À compléter — statut par pièce (Complet / À confirmer)
A16: 5 | B16: E. Renforcement de capacités / formations | C16: 9000 | D16: 4200 | E16: =C16-D16 -> 4800 | F16: =IF(C16=0,0,D16/C16) -> 0.46666667 | G16: À compléter — statut par pièce (Complet / À confirmer)
A17: 6 | B17: F. Suivi-évaluation (MEAL) | C17: 11000 | D17: 6800 | E17: =C17-D17 -> 4200 | F17: =IF(C17=0,0,D17/C17) -> 0.61818182 | G17: À compléter — statut par pièce (Complet / À confirmer)
A18: 7 | B18: G. Coûts de support / overhead | C18: 14000 | D18: 9950 | E18: =C18-D18 -> 4050 | F18: =IF(C18=0,0,D18/C18) -> 0.71071429 | G18: À compléter — statut par pièce (Complet / À confirmer)
A19: 8 | B19: H. Imprévus / ligne de contingence | C19: 6000 | D19: 0 | E19: =C19-D19 -> 6000 | F19: =IF(C19=0,0,D19/C19) -> 0 | G19: À compléter — statut par pièce (Complet / À confirmer)
B20: TOTAL PROJET | C20: =SUM(C12:C19) -> 263000 | D20: =SUM(D12:D19) -> 209150 | E20: =C20-D20 -> 53850 | F20: =IF(C20=0,0,D20/C20) -> 0.79524715
A22: Seuil de flexibilité budgétaire du bailleur (ex. 10 % chez ECHO) :
B23: Seuil de flexibilité (%) | C23: 0.1 | D23: Toute rubrique dont le % consommé dépasse le budget alloué + ce seuil doit déclencher une vérification d'imputation ou une demande d'avenant avant soumission.
A25: Colonne « Justificatifs » : ne marquer une ligne « Complet » que si les 3 pièces du 3-way match (contrat/bon de commande, facture, preuve de paiement) sont réunies et se recoupent. Voir 01-théorie.md et 02-outils.md du Module 05.

Sheet Synthèse
A1: SYNTHÈSE & PRÉPARATION À LA SOUMISSION
A2: Calculée automatiquement à partir de l'onglet « Rapport Financier » — ne pas modifier les formules.
A4: Indicateur | B4: Valeur | D4: Interprétation
A5: Budget total du projet | B5: ='Rapport Financier'!C20 -> 263000 | D5: Budget global toutes rubriques confondues.
A6: Dépenses cumulées à date | B6: ='Rapport Financier'!D20 -> 209150 | D6: Doit correspondre à la comptabilité analytique de la période rapportée.
A7: Solde disponible | B7: ='Rapport Financier'!E20 -> 53850 | D7: À rapprocher du taux d'avancement programmatique réel.
A8: % global consommé | B8: ='Rapport Financier'!F20 -> 0.79524715 | D8: Comparer à l'avancement calendaire du projet — un écart important doit être expliqué.
A9: Nombre de rubriques | B9: =COUNTA('Rapport Financier'!B12:B19) -> 8 | D9: Nombre de lignes budgétaires actives sur le projet.
A10: Rubriques à justificatifs incomplets | B10: =COUNTIF('Rapport Financier'!G12:G19,"*confirmer*") -> 8 | D10: Doit être à zéro avant toute soumission au bailleur.
A12: Avant soumission : vérifier que « Rubriques à justificatifs incomplets » = 0 et que ce rapport a été réconcilié avec le rapport narratif via checklist-reconciliation-finance-programme.docx.
