Workbook

Sheet Tableau de bord
A1: TABLEAU DE BORD - READINESS AUDIT EXTERNE MULTI-DOMAINES
A2: Formation en Audit, Transparence et Conformite des ONGs - Module 09 - BK-BOOST Ltd.
A4: Domaine | B4: Points de controle | C4: Disponibles | D4: % Pret | E4: A traiter (En cours + Manquant) | F4: Statut global
A5: Finance | B5: =COUNTA(Finance!$A$5:$A$10) -> 6 | C5: =COUNTIF(Finance!$D$5:$D$10,"Disponible") -> 4 | D5: =IF(B5=0,"",C5/B5) -> 0.66666667 | E5: =B5-C5 -> 2 | F5: =IF(B5=0,"-",IF(COUNTIF(Finance!$D$5:$D$10,"Manquant")>0,"A COMPLETER",IF(COUNTIF(Finance!$D$5:$D$10,"En cours")>0,"EN COURS","PRET"))) -> A COMPLETER
A6: SCM - Achats | B6: =COUNTA('SCM - Achats'!$A$5:$A$10) -> 6 | C6: =COUNTIF('SCM - Achats'!$D$5:$D$10,"Disponible") -> 4 | D6: =IF(B6=0,"",C6/B6) -> 0.66666667 | E6: =B6-C6 -> 2 | F6: =IF(B6=0,"-",IF(COUNTIF('SCM - Achats'!$D$5:$D$10,"Manquant")>0,"A COMPLETER",IF(COUNTIF('SCM - Achats'!$D$5:$D$10,"En cours")>0,"EN COURS","PRET"))) -> A COMPLETER
A7: RH | B7: =COUNTA(RH!$A$5:$A$10) -> 6 | C7: =COUNTIF(RH!$D$5:$D$10,"Disponible") -> 4 | D7: =IF(B7=0,"",C7/B7) -> 0.66666667 | E7: =B7-C7 -> 2 | F7: =IF(B7=0,"-",IF(COUNTIF(RH!$D$5:$D$10,"Manquant")>0,"A COMPLETER",IF(COUNTIF(RH!$D$5:$D$10,"En cours")>0,"EN COURS","PRET"))) -> A COMPLETER
A8: Programme | B8: =COUNTA(Programme!$A$5:$A$10) -> 6 | C8: =COUNTIF(Programme!$D$5:$D$10,"Disponible") -> 4 | D8: =IF(B8=0,"",C8/B8) -> 0.66666667 | E8: =B8-C8 -> 2 | F8: =IF(B8=0,"-",IF(COUNTIF(Programme!$D$5:$D$10,"Manquant")>0,"A COMPLETER",IF(COUNTIF(Programme!$D$5:$D$10,"En cours")>0,"EN COURS","PRET"))) -> A COMPLETER
A9: TOUTE L'ORGANISATION | B9: =SUM(B5:B8) -> 24 | C9: =SUM(C5:C8) -> 16 | D9: =IF(B9=0,"",C9/B9) -> 0.66666667 | E9: =B9-C9 -> 8 | F9: =IF(D9=1,"PRET","A COMPLETER") -> A COMPLETER
A11: Calcule automatiquement a partir des onglets par domaine - ne pas modifier manuellement les colonnes B a F.

Sheet Finance
A1: CHECKLIST DE PREPARATION AUDIT EXTERNE - FINANCE
A2: Formation en Audit, Transparence et Conformite des ONGs - Module 09 - BK-BOOST Ltd.
A4: Point de controle | B4: Preuve documentaire attendue | C4: Responsable | D4: Statut | E4: Emplacement (dossier partage) | F4: Derniere verification | G4: Commentaire
A5: Dossier de preparation a l'audit finance transmis par le Finance Manager | B5: Dossier complet cf. checklist Finance (Formation Gestion Financiere, Module 06) | C5: Finance Manager | D5: Disponible | E5: Drive/Finance/Audit | F5: 46254
A6: Cle de repartition des couts partages entre projets validee et documentee | B6: Note de methode signee + tableau de repartition par projet | C6: Finance Manager | D6: Disponible | E6: Drive/Finance/Repartition | F6: 46252
A7: Rapprochements bancaires signes pour toute la periode sous audit | B7: Rapprochements mensuels signes Finance Officer + superviseur | C7: Finance Officer | D7: En cours | E7: Drive/Finance/Banque | F7: 46256
A8: Suivi budgetaire par bailleur a jour et coherent avec les rapports financiers | B8: BFU (Budget Follow-Up) par bailleur, derniere version | C8: Finance Manager | D8: Disponible | E8: Drive/Finance/BFU | F8: 46249
A9: Registre des immobilisations a jour avec preuve d'existence physique recente | B9: Registre + PV d'inventaire physique signe | C9: Finance Manager | D9: Manquant | E9: Drive/Finance/Immobilisations | F9: 46233 | G9: Inventaire physique a planifier avant la mission
A10: Points en suspens du dernier audit externe et statut de cloture | B10: Plan d'action correctif precedent + preuves de cloture | C10: Compliance Officer | D10: Disponible | E10: Drive/Audit/Suivi | F10: 46244
A12: Statut : Disponible / En cours / Manquant - a mettre a jour en continu, pas seulement a l'annonce de la mission.

Sheet SCM - Achats
A1: CHECKLIST DE PREPARATION AUDIT EXTERNE - SCM - ACHATS
A2: Formation en Audit, Transparence et Conformite des ONGs - Module 09 - BK-BOOST Ltd.
A4: Point de controle | B4: Preuve documentaire attendue | C4: Responsable | D4: Statut | E4: Emplacement (dossier partage) | F4: Derniere verification | G4: Commentaire
A5: Dossiers d'achats complets pour l'echantillon probable (achats > seuil de derogation) | B5: 3 devis ou justification de derogation, bon de commande, contrat | C5: Procurement Manager | D5: Disponible | E5: Drive/SCM/Achats | F5: 46253
A6: Registre des contrats fournisseurs actifs a jour avec dates d'echeance | B6: Registre contrats + copies signees | C6: Procurement Officer | D6: Disponible | E6: Drive/SCM/Contrats | F6: 46246
A7: PV de reception et bons de livraison rapproches aux factures | B7: PV de reception signes + factures correspondantes | C7: Store Keeper | D7: En cours | E7: Drive/SCM/Reception | F7: 46255 | G7: Rapprochement en cours sur aout
A8: Inventaire physique du stock realise et rapproche a la fiche de stock | B8: PV d'inventaire physique + fiche de stock a jour | C8: Logistics Manager | D8: Disponible | E8: Drive/SCM/Stock | F8: 46239
A9: Justificatifs de derogation a la procedure d'achat (urgence, source unique) archives | B9: Note de derogation validee par le niveau hierarchique requis | C9: Procurement Manager | D9: Manquant | E9: Drive/SCM/Derogations | F9: 46231 | G9: Deux dossiers a completer
A10: Contrats de location vehicules et attestations d'assurance a jour | B10: Contrats + attestations d'assurance en cours de validite | C10: Logistics Manager | D10: Disponible | E10: Drive/SCM/Flotte | F10: 46248
A12: Statut : Disponible / En cours / Manquant - a mettre a jour en continu, pas seulement a l'annonce de la mission.

Sheet RH
A1: CHECKLIST DE PREPARATION AUDIT EXTERNE - RH
A2: Formation en Audit, Transparence et Conformite des ONGs - Module 09 - BK-BOOST Ltd.
A4: Point de controle | B4: Preuve documentaire attendue | C4: Responsable | D4: Statut | E4: Emplacement (dossier partage) | F4: Derniere verification | G4: Commentaire
A5: Dossiers du personnel complets pour l'echantillon probable | B5: Contrat, CV, diplomes, evaluation annuelle | C5: RH Manager | D5: Disponible | E5: Drive/RH/Dossiers-Personnel | F5: 46251
A6: Registre de paie rapproche aux contrats actifs et aux releves de presence | B6: Livre de paie + feuilles de presence signees | C6: RH Manager | D6: En cours | E6: Drive/RH/Paie | F6: 46257
A7: Preuve d'existence physique recente des employes sur la liste de paie | B7: PV de pointage physique ou biometrique recent | C7: Compliance Officer | D7: Manquant | E7: Drive/RH/Controle-Effectifs | F7: 46228 | G7: Pointage physique a organiser avant la mission
A8: Politique de delegation de signature a jour et signee par la Direction | B8: Document de delegation signe, versions anterieures archivees | C8: Direction Pays | D8: Disponible | E8: Drive/RH/Gouvernance | F8: 46235
A9: Dossiers de depart complets pour le personnel sorti sur la periode | B9: Solde de tout compte + decharge signee | C9: RH Manager | D9: Disponible | E9: Drive/RH/Departs | F9: 46243
A10: Registre des formations et habilitations obligatoires a jour | B10: Attestations de formation securite et code de conduite | C10: RH Manager | D10: Disponible | E10: Drive/RH/Formations | F10: 46245
A12: Statut : Disponible / En cours / Manquant - a mettre a jour en continu, pas seulement a l'annonce de la mission.

Sheet Programme
A1: CHECKLIST DE PREPARATION AUDIT EXTERNE - PROGRAMME
A2: Formation en Audit, Transparence et Conformite des ONGs - Module 09 - BK-BOOST Ltd.
A4: Point de controle | B4: Preuve documentaire attendue | C4: Responsable | D4: Statut | E4: Emplacement (dossier partage) | F4: Derniere verification | G4: Commentaire
A5: Rapports narratifs bailleurs archives et coherents avec les depenses comptabilisees | B5: Rapports narratifs finaux + versions transmises au bailleur | C5: Program Manager | D5: Disponible | E5: Drive/Programme/Rapports | F5: 46250
A6: Listes de beneficiaires et preuves de distribution disponibles pour l'echantillon | B6: Listes signees ou emargees, photos si prevu par le protocole | C6: Program Manager | D6: Disponible | E6: Drive/Programme/Distributions | F6: 46247
A7: Indicateurs de suivi M&E documentes et coherents avec les rapports financiers | B7: Base de donnees M&E + tableau de bord indicateurs | C7: MEAL Officer | D7: En cours | E7: Drive/Programme/MEAL | F7: 46254
A8: Accords de partenariat et de sous-subvention archives avec suivi des obligations | B8: Accords signes + rapports de suivi partenaire | C8: Program Manager | D8: Disponible | E8: Drive/Programme/Partenariats | F8: 46238
A9: Validations bailleur des modifications budgetaires (no-cost extension, reallocation) | B9: Courriers ou emails d'approbation bailleur | C9: Program Manager | D9: Manquant | E9: Drive/Programme/Modifications | F9: 46225 | G9: Une validation orale a faire confirmer par ecrit
A10: Dossier de la cle de repartition analytique des couts partages entre projets | B10: Meme cle de repartition que celle validee par Finance - coherence a verifier | C10: Program Manager | D10: Disponible | E10: Drive/Programme/Repartition | F10: 46252 | G10: Cf. onglet Finance, ligne 2
A12: Statut : Disponible / En cours / Manquant - a mettre a jour en continu, pas seulement a l'annonce de la mission.
